{
  "version": "5.3.1",
  "flags": {},
  "shapes": [
    {
      "label": "Pawn",
      "points": [
        [
          331.6429443359375,
          316.1697082519531
        ],
        [
          375.5957946777344,
          371.4449462890625
        ]
      ],
      "group_id": null,
      "shape_type": "rectangle",
      "flags": {}
    },
    {
      "label": "Pawn",
      "points": [
        [
          261.4920349121094,
          297.0137634277344
        ],
        [
          292.5967712402344,
          332.3349609375
        ]
      ],
      "group_id": null,
      "shape_type": "rectangle",
      "flags": {}
    },
    {
      "label": "Pawn",
      "points": [
        [
          297.2478332519531,
          200.3963165283203
        ],
        [
          329.0373840332031,
          245.868896484375
        ]
      ],
      "group_id": null,
      "shape_type": "rectangle",
      "flags": {}
    },
    {
      "label": "Pawn",
      "points": [
        [
          304.794677734375,
          312.84423828125
        ],
        [
          339.2771911621094,
          348.6387023925781
        ]
      ],
      "group_id": null,
      "shape_type": "rectangle",
      "flags": {}
    }
  ],
  "imagePath": "frame_14950.jpg",
  "imageData": null,
  "imageHeight": 852,
  "imageWidth": 480
}