{
  "version": "5.3.1",
  "flags": {},
  "shapes": [
    {
      "label": "Pawn",
      "points": [
        [
          148.0491485595703,
          191.53915405273438
        ],
        [
          183.34063720703125,
          235.00193786621094
        ]
      ],
      "group_id": null,
      "shape_type": "rectangle",
      "flags": {}
    },
    {
      "label": "Pawn",
      "points": [
        [
          186.21331787109375,
          187.01344299316406
        ],
        [
          230.65321350097656,
          229.02874755859375
        ]
      ],
      "group_id": null,
      "shape_type": "rectangle",
      "flags": {}
    }
  ],
  "imagePath": "frame_24725.jpg",
  "imageData": null,
  "imageHeight": 852,
  "imageWidth": 480
}