{
  "version": "5.3.1",
  "flags": {},
  "shapes": [
    {
      "label": "Pawn",
      "points": [
        [
          318.3844299316406,
          314.75103759765625
        ],
        [
          374.4161071777344,
          366.7154541015625
        ]
      ],
      "group_id": null,
      "shape_type": "rectangle",
      "flags": {}
    },
    {
      "label": "Pawn",
      "points": [
        [
          330.09515380859375,
          365.7458190917969
        ],
        [
          373.7494812011719,
          406.8825988769531
        ]
      ],
      "group_id": null,
      "shape_type": "rectangle",
      "flags": {}
    },
    {
      "label": "Pawn",
      "points": [
        [
          334.3906555175781,
          257.38751220703125
        ],
        [
          372.7759094238281,
          308.10089111328125
        ]
      ],
      "group_id": null,
      "shape_type": "rectangle",
      "flags": {}
    }
  ],
  "imagePath": "frame_12300.jpg",
  "imageData": null,
  "imageHeight": 852,
  "imageWidth": 480
}