{
  "version": "5.3.1",
  "flags": {},
  "shapes": [
    {
      "label": "Pawn",
      "points": [
        [
          161.05799865722656,
          333.7315673828125
        ],
        [
          213.08580017089844,
          426.20953369140625
        ]
      ],
      "group_id": null,
      "shape_type": "rectangle",
      "flags": {}
    },
    {
      "label": "Pawn",
      "points": [
        [
          209.6967315673828,
          372.22857666015625
        ],
        [
          248.690185546875,
          432.9454040527344
        ]
      ],
      "group_id": null,
      "shape_type": "rectangle",
      "flags": {}
    },
    {
      "label": "Pawn",
      "points": [
        [
          139.60890197753906,
          433.6271667480469
        ],
        [
          213.06503295898438,
          506.49676513671875
        ]
      ],
      "group_id": null,
      "shape_type": "rectangle",
      "flags": {}
    }
  ],
  "imagePath": "frame_4050.jpg",
  "imageData": null,
  "imageHeight": 852,
  "imageWidth": 480
}