{
  "version": "5.3.1",
  "flags": {},
  "shapes": [
    {
      "label": "Pawn",
      "points": [
        [
          285.55755615234375,
          482.1665344238281
        ],
        [
          331.549072265625,
          537.4837646484375
        ]
      ],
      "group_id": null,
      "shape_type": "rectangle",
      "flags": {}
    },
    {
      "label": "Pawn",
      "points": [
        [
          347.3361511230469,
          331.58734130859375
        ],
        [
          383.2057189941406,
          367.7842102050781
        ]
      ],
      "group_id": null,
      "shape_type": "rectangle",
      "flags": {}
    }
  ],
  "imagePath": "frame_22850.jpg",
  "imageData": null,
  "imageHeight": 852,
  "imageWidth": 480
}