{
  "version": "5.3.1",
  "flags": {},
  "shapes": [
    {
      "label": "Pawn",
      "points": [
        [
          317.71746826171875,
          393.33251953125
        ],
        [
          363.6660461425781,
          439.99664306640625
        ]
      ],
      "group_id": null,
      "shape_type": "rectangle",
      "flags": {}
    },
    {
      "label": "Pawn",
      "points": [
        [
          177.46031188964844,
          578.9297485351562
        ],
        [
          243.27024841308594,
          655.710205078125
        ]
      ],
      "group_id": null,
      "shape_type": "rectangle",
      "flags": {}
    },
    {
      "label": "Pawn",
      "points": [
        [
          86.88518524169922,
          496.6220397949219
        ],
        [
          151.14956665039062,
          572.3941040039062
        ]
      ],
      "group_id": null,
      "shape_type": "rectangle",
      "flags": {}
    }
  ],
  "imagePath": "frame_23225.jpg",
  "imageData": null,
  "imageHeight": 852,
  "imageWidth": 480
}