{
  "version": "5.3.1",
  "flags": {},
  "shapes": [
    {
      "label": "Pawn",
      "points": [
        [
          300.6423034667969,
          367.73291015625
        ],
        [
          344.2810974121094,
          409.9105529785156
        ]
      ],
      "group_id": null,
      "shape_type": "rectangle",
      "flags": {}
    },
    {
      "label": "Pawn",
      "points": [
        [
          340.5738220214844,
          322.4265441894531
        ],
        [
          379.8656005859375,
          361.033447265625
        ]
      ],
      "group_id": null,
      "shape_type": "rectangle",
      "flags": {}
    },
    {
      "label": "Pawn",
      "points": [
        [
          293.32440185546875,
          309.4626770019531
        ],
        [
          334.37139892578125,
          361.52691650390625
        ]
      ],
      "group_id": null,
      "shape_type": "rectangle",
      "flags": {}
    }
  ],
  "imagePath": "frame_16400.jpg",
  "imageData": null,
  "imageHeight": 852,
  "imageWidth": 480
}