{
  "version": "5.3.1",
  "flags": {},
  "shapes": [
    {
      "label": "Pawn",
      "points": [
        [
          230.40431213378906,
          360.2194519042969
        ],
        [
          275.05126953125,
          410.4538269042969
        ]
      ],
      "group_id": null,
      "shape_type": "rectangle",
      "flags": {}
    },
    {
      "label": "Pawn",
      "points": [
        [
          308.2065124511719,
          314.3227844238281
        ],
        [
          351.869140625,
          359.0419616699219
        ]
      ],
      "group_id": null,
      "shape_type": "rectangle",
      "flags": {}
    }
  ],
  "imagePath": "frame_29575.jpg",
  "imageData": null,
  "imageHeight": 852,
  "imageWidth": 480
}