{
  "version": "5.3.1",
  "flags": {},
  "shapes": [
    {
      "label": "Pawn",
      "points": [
        [
          132.8817901611328,
          238.4775390625
        ],
        [
          163.24615478515625,
          286.683837890625
        ]
      ],
      "group_id": null,
      "shape_type": "rectangle",
      "flags": {}
    },
    {
      "label": "Pawn",
      "points": [
        [
          139.86244201660156,
          363.4977722167969
        ],
        [
          165.43585205078125,
          399.5877990722656
        ]
      ],
      "group_id": null,
      "shape_type": "rectangle",
      "flags": {}
    },
    {
      "label": "Pawn",
      "points": [
        [
          126.25700378417969,
          302.8768005371094
        ],
        [
          155.9796905517578,
          351.5028076171875
        ]
      ],
      "group_id": null,
      "shape_type": "rectangle",
      "flags": {}
    }
  ],
  "imagePath": "frame_6725.jpg",
  "imageData": null,
  "imageHeight": 852,
  "imageWidth": 480
}