{
  "version": "5.3.1",
  "flags": {},
  "shapes": [
    {
      "label": "Pawn",
      "points": [
        [
          309.1080627441406,
          417.5302429199219
        ],
        [
          360.0177917480469,
          458.9356689453125
        ]
      ],
      "group_id": null,
      "shape_type": "rectangle",
      "flags": {}
    },
    {
      "label": "Pawn",
      "points": [
        [
          299.448486328125,
          498.0196838378906
        ],
        [
          327.34857177734375,
          545.0040893554688
        ]
      ],
      "group_id": null,
      "shape_type": "rectangle",
      "flags": {}
    },
    {
      "label": "Pawn",
      "points": [
        [
          115.66204833984375,
          464.5272521972656
        ],
        [
          175.19639587402344,
          513.2716064453125
        ]
      ],
      "group_id": null,
      "shape_type": "rectangle",
      "flags": {}
    },
    {
      "label": "Pawn",
      "points": [
        [
          316.2809753417969,
          339.7197265625
        ],
        [
          353.82476806640625,
          369.8067626953125
        ]
      ],
      "group_id": null,
      "shape_type": "rectangle",
      "flags": {}
    }
  ],
  "imagePath": "frame_30725.jpg",
  "imageData": null,
  "imageHeight": 852,
  "imageWidth": 480
}