{
  "version": "5.3.1",
  "flags": {},
  "shapes": [
    {
      "label": "Pawn",
      "points": [
        [
          302.6873779296875,
          367.2828063964844
        ],
        [
          345.6390075683594,
          417.0226745605469
        ]
      ],
      "group_id": null,
      "shape_type": "rectangle",
      "flags": {}
    },
    {
      "label": "Pawn",
      "points": [
        [
          275.4958190917969,
          311.6763000488281
        ],
        [
          320.6653747558594,
          377.19256591796875
        ]
      ],
      "group_id": null,
      "shape_type": "rectangle",
      "flags": {}
    },
    {
      "label": "Pawn",
      "points": [
        [
          311.16888427734375,
          268.7721252441406
        ],
        [
          354.4554443359375,
          291.924560546875
        ]
      ],
      "group_id": null,
      "shape_type": "rectangle",
      "flags": {}
    }
  ],
  "imagePath": "frame_16375.jpg",
  "imageData": null,
  "imageHeight": 852,
  "imageWidth": 480
}